MANIFEST.in
README.rst
setup.py
HeyAthena.egg-info/PKG-INFO
HeyAthena.egg-info/SOURCES.txt
HeyAthena.egg-info/dependency_links.txt
HeyAthena.egg-info/requires.txt
HeyAthena.egg-info/top_level.txt
athena/__init__.py
athena/__main__.py
athena/apis.py
athena/brain.py
athena/config.py
athena/log.py
athena/mods.py
athena/settings.py
athena/stt.py
athena/tts.py
athena/api_library/__init__.py
athena/api_library/geo_info_api.py
athena/api_library/ifttt_api.py
athena/api_library/sms_text_api.py
athena/api_library/user_api.py
athena/api_library/voice_browse_api.py
athena/chrome/.DS_Store
athena/chrome/linux32/chromedriver
athena/chrome/mac64/.DS_Store
athena/chrome/mac64/chromedriver
athena/chrome/win32/chromedriver.exe
athena/classes/__init__.py
athena/classes/api.py
athena/classes/input_field.py
athena/classes/module.py
athena/classes/response.py
athena/classes/task.py
athena/data/media/double-beep.mp3
athena/data/media/godj.mp3
athena/data/media/responses/error.mp3
athena/data/media/responses/test.mp3
athena/modules/__init__.py
athena/modules/active/__init__.py
athena/modules/active/athena_control.py
athena/modules/active/conversation.py
athena/modules/active/geo_info.py
athena/modules/active/google.py
athena/modules/active/hello_world.py
athena/modules/active/music.py
athena/modules/active/shop.py
athena/modules/active/sms_text.py
athena/modules/active/twitter.py
athena/modules/active/uber.py
athena/modules/active/voice_browse.py
athena/modules/active/wolfram.py
athena/modules/passive/__init__.py
athena/tests/__init__.py
athena/tests/dependencies_test.py
athena/tests/input_test.py
athena/tests/mic_test.py